microProcessador/multiplex8x1.vhd
library IEEE;
use IEEE.std_logic_1164.all;
use IEEE.numeric_std.all;

entity multiplex8x1 is
    port(
        entr0, entr1, entr2, entr3, entr4, entr5, entr6, entr7: in std_logic;
        selec0, selec1, selec2:                                 in std_logic;
        output:                                                 out std_logic
    );
end entity multiplex8x1;
architecture rtl of multiplex8x1 is
begin
    output <= entr0 when selec2='0' and selec1='0' and selec0='0' else
              entr1 when selec2='0' and selec1='0' and selec0='1' else
              entr2 when selec2='0' and selec1='1' and selec0='0' else
              entr3 when selec2='0' and selec1='1' and selec0='1' else
              entr4 when selec2='1' and selec1='0' and selec0='0' else
              entr5 when selec2='1' and selec1='0' and selec0='1' else
              entr6 when selec2='1' and selec1='1' and selec0='0' else
              entr7 when selec2='1' and selec1='1' and selec0='1' else
              '0';
end architecture rtl;

microProcessador/multiplex8x1_testbench.vhd
library IEEE;
use IEEE.std_logic_1164.all;
use IEEE.numeric_std.all;

entity multiplex8x1_testbench is
end entity;

architecture rtl of multiplex8x1_testbench is
    component multiplex8x1 is
        port
        (
            entr0  : IN std_logic ;
            entr1  : IN std_logic ;
            entr2  : IN std_logic ;
            entr3  : IN std_logic ;
            entr4  : IN std_logic ;
            entr5  : IN std_logic ;
            entr6  : IN std_logic ;
            entr7  : IN std_logic ;
            selec0 : IN std_logic ;
            selec1 : IN std_logic ;
            selec2 : IN std_logic ;
            output : OUT std_logic
        );
    end component;

    signal entr0, entr1, entr2, entr3, entr4, entr5, entr6, entr7, selec0, selec1, selec2, output: std_logic;

begin
    uut: multiplex8x1 port map (
        entr0 => entr0,
        entr1 => entr1,
        entr2 => entr2,
        entr3 => entr3,
        entr4 => entr4,
        entr5 => entr5,
        entr6 => entr6,
        entr7 => entr7,
        selec0 => selec0,
        selec1 => selec1,
        selec2 => selec2,
        output => output
    );
    
    process
    begin
        entr0 <= '0';
        entr1 <= '0';
        entr5 <= '0';
        entr3 <= '1';
        entr7 <= '1';
        entr2 <= '0';
        entr4 <= '0';
        entr6 <= '0';
        selec0 <= '1';
        selec1 <= '1';
        selec2 <= '1';
        wait for 50 ns;
        entr2 <= '1';
        entr4 <= '0';
        entr6 <= '0';
        selec0 <= '0';
        selec1 <= '1';
        selec2 <= '0';
        wait for 50 ns;
        entr2 <= '0';
        entr4 <= '1';
        entr6 <= '0';
        selec0 <= '0';
        selec1 <= '0';
        selec2 <= '1';
        wait for 50 ns;
        entr2 <= '1';
        entr4 <= '1';
        entr6 <= '0';
        selec0 <= '1';
        selec1 <= '1';
        selec2 <= '0';
        wait for 50 ns;
        entr2 <= '0';
        entr4 <= '0';
        entr6 <= '1';
        selec0 <= '0';
        selec1 <= '0';
        selec2 <= '1';
        wait for 50 ns;
        entr2 <= '1';
        entr4 <= '0';
        entr6 <= '1';
        selec0 <= '1';
        selec1 <= '0';
        selec2 <= '1';
        wait for 50 ns;
        entr2 <= '0';
        entr4 <= '1';
        entr6 <= '1';
        selec0 <= '0';
        selec1 <= '1';
        selec2 <= '1';
        wait for 50 ns;
        entr2 <= '1';
        entr4 <= '1';
        entr6 <= '1';
        selec0 <= '1';
        selec1 <= '1';
        selec2 <= '1';
        wait;
    end process;

end architecture rtl;

microProcessador/multiplex8x1_testbench.vcd
$date
  Thu Sep 15 17:08:41 2022
$end
$version
  GHDL v0
$end
$timescale
  1 fs
$end
$scope module standard $end
$upscope $end
$scope module textio $end
$upscope $end
$scope module std_logic_1164 $end
$upscope $end
$scope module numeric_std $end
$upscope $end
$scope module multiplex8x1_testbench $end
$var reg 1 ! entr0 $end
$var reg 1 " entr1 $end
$var reg 1 # entr2 $end
$var reg 1 $ entr3 $end
$var reg 1 % entr4 $end
$var reg 1 & entr5 $end
$var reg 1 ' entr6 $end
$var reg 1 ( entr7 $end
$var reg 1 ) selec0 $end
$var reg 1 * selec1 $end
$var reg 1 + selec2 $end
$var reg 1 , output $end
$scope module uut $end
$var reg 1 - entr0 $end
$var reg 1 . entr1 $end
$var reg 1 / entr2 $end
$var reg 1 0 entr3 $end
$var reg 1 1 entr4 $end
$var reg 1 2 entr5 $end
$var reg 1 3 entr6 $end
$var reg 1 4 entr7 $end
$var reg 1 5 selec0 $end
$var reg 1 6 selec1 $end
$var reg 1 7 selec2 $end
$var reg 1 8 output $end
$upscope $end
$upscope $end
$enddefinitions $end
#0
0!
0"
0#
1$
0%
0&
0'
1(
1)
1*
1+
1,
0-
0.
0/
10
01
02
03
14
15
16
17
18
#50000000
1#
0)
0+
1/
05
07
#100000000
0#
1%
0*
1+
0/
11
06
17
#150000000
1#
1)
1*
0+
1/
15
16
07
#200000000
0#
0%
1'
0)
0*
1+
0,
0/
01
13
05
06
17
08
#250000000
1#
1)
1/
15
#300000000
0#
1%
0)
1*
1,
0/
11
05
16
18
#350000000
1#
1)
1/
15
