microProcessador/count_one.vhd
library IEEE;
use IEEE.std_logic_1164.all;
use IEEE.numeric_std.all;

entity count_one is
   port
   (
      data_pc:  in unsigned (15 downto 0);
      clk:      in std_logic;
      data_out: out unsigned (15 downto 0)
   );
end entity count_one;

architecture rtl of count_one is
   signal counting: unsigned (15 downto 0);
begin
   process(clk)
   begin
      if rising_edge(clk) then
         counting <= data_pc + "0000000000000001";
      end if;
   end process;

data_out <= counting;

end architecture rtl;

microProcessador/program_counter.vhd
library IEEE;
use IEEE.std_logic_1164.all;
use IEEE.numeric_std.all;

entity program_counter is
   port
   (
      data_in:                   in unsigned (15 downto 0);
      clk, write_en, reset:      in std_logic;
      data_out:                  out unsigned (15 downto 0)
   );
end entity program_counter;

architecture rtl of program_counter is
   signal data_sig : unsigned (15 downto 0);
   
begin
   
   process(clk, reset, write_en)
   begin
       if reset='1' then 
           data_sig <= "0000000000000000";
       elsif write_en='1' then
           if rising_edge(clk) then
               data_sig <= data_in;
           end if;
       end if;
   end process;
   
   data_out <= data_sig;
end architecture rtl;

microProcessador/pc_count_one.vhd
library IEEE;
use IEEE.std_logic_1164.all;
use IEEE.numeric_std.all;

entity pc_count_one is
    port (
        clk      : in std_logic;
        write_en : in std_logic;
        reset    : in std_logic;
        output_pc: out unsigned (15 downto 0)
    );
end entity;

architecture rtl of pc_count_one is
    component program_counter is
        port
        (
            data_in:                   in unsigned (15 downto 0);
            clk, write_en, reset:      in std_logic;
            data_out:                  out unsigned (15 downto 0)
        );
    end component;

    component count_one is
        port
        (
            data_pc:  in unsigned (15 downto 0);
            clk:      in std_logic;
            data_out: out unsigned (15 downto 0)
        );
    end component;

    signal data_out_pc_sig, data_out_count_sig: unsigned (15 downto 0);

begin

    pc: program_counter port map (data_in => data_out_count_sig, clk => clk, write_en => write_en, reset => reset, data_out => data_out_pc_sig);
    count: count_one port map (data_pc => data_out_pc_sig, clk => clk, data_out => data_out_count_sig);

    output_pc <= data_out_pc_sig;

end architecture rtl;

microProcessador/pc_count_one_testbench.vhd
library IEEE;
use IEEE.std_logic_1164.all;
use IEEE.numeric_std.all;

entity pc_count_one_testbench is
end entity;

architecture rtl of pc_count_one_testbench is
    component pc_count_one is
        port
        (
            clk      : in std_logic;
            write_en : in std_logic;
            reset    : in std_logic;
            output_pc: out unsigned (15 downto 0) 
        );
    end component;
        
    signal clk, write_en: std_logic;
    signal finish, reset: std_logic;
    signal output_pc    : unsigned (15 downto 0); 
    constant time_period: time := 50 ns;
    
    begin
    uut: pc_count_one port map
    (
        clk       => clk,
        write_en  => write_en,
        reset     => reset,
        output_pc => output_pc
    );
    
    reset_global:
    process
    begin
        reset <= '1';
        wait for time_period;
        reset <= '0';
        wait;
    end process;
    
    simulation_time:
    process
    begin
        wait for 1000 ns;
            finish <= '1';
        wait;
    end process;
    
    time_clk:
    process
    begin
        while finish /= '1' loop
            clk <= '0';
            wait for time_period/2;
            clk <= '1';
            wait for time_period/2;
        end loop;
        wait;
    end process;

    write_en_process:
    process
    begin
        write_en <= '1';
        wait;
    end process;

    process
    begin
        wait for time_period; -- visualiza o soma 1 a cada 2 clocks
        wait for time_period;
        wait for time_period;
        wait for time_period;
        wait for time_period;
        wait for time_period;
        wait for time_period;
        wait for time_period;
        wait for time_period;
        wait;
    end process;

end architecture;

microProcessador/pc_count_one_testbench.vcd
$date
  Wed Oct 19 22:03:57 2022
$end
$version
  GHDL v0
$end
$timescale
  1 fs
$end
$scope module standard $end
$upscope $end
$scope module textio $end
$upscope $end
$scope module std_logic_1164 $end
$upscope $end
$scope module numeric_std $end
$upscope $end
$scope module pc_count_one_testbench $end
$var reg 1 ! clk $end
$var reg 1 " write_en $end
$var reg 1 # finish $end
$var reg 1 $ reset $end
$var reg 16 % output_pc[15:0] $end
$scope module uut $end
$var reg 1 & clk $end
$var reg 1 ' write_en $end
$var reg 1 ( reset $end
$var reg 16 ) output_pc[15:0] $end
$var reg 16 * data_out_pc_sig[15:0] $end
$var reg 16 + data_out_count_sig[15:0] $end
$scope module pc $end
$var reg 16 , data_in[15:0] $end
$var reg 1 - clk $end
$var reg 1 . write_en $end
$var reg 1 / reset $end
$var reg 16 0 data_out[15:0] $end
$var reg 16 1 data_sig[15:0] $end
$upscope $end
$scope module count $end
$var reg 16 2 data_pc[15:0] $end
$var reg 1 3 clk $end
$var reg 16 4 data_out[15:0] $end
$var reg 16 5 counting[15:0] $end
$upscope $end
$upscope $end
$upscope $end
$enddefinitions $end
#0
0!
1"
U#
1$
b0000000000000000 %
0&
1'
1(
b0000000000000000 )
b0000000000000000 *
bUUUUUUUUUUUUUUUU +
bUUUUUUUUUUUUUUUU ,
0-
1.
1/
b0000000000000000 0
b0000000000000000 1
b0000000000000000 2
03
bUUUUUUUUUUUUUUUU 4
bUUUUUUUUUUUUUUUU 5
#25000000
1!
1&
b0000000000000001 +
b0000000000000001 ,
1-
13
b0000000000000001 4
b0000000000000001 5
#50000000
0!
0$
0&
0(
0-
0/
03
#75000000
1!
b0000000000000001 %
1&
b0000000000000001 )
b0000000000000001 *
1-
b0000000000000001 0
b0000000000000001 1
b0000000000000001 2
13
#100000000
0!
0&
0-
03
#125000000
1!
1&
b0000000000000010 +
b0000000000000010 ,
1-
13
b0000000000000010 4
b0000000000000010 5
#150000000
0!
0&
0-
03
#175000000
1!
b0000000000000010 %
1&
b0000000000000010 )
b0000000000000010 *
1-
b0000000000000010 0
b0000000000000010 1
b0000000000000010 2
13
#200000000
0!
0&
0-
03
#225000000
1!
1&
b0000000000000011 +
b0000000000000011 ,
1-
13
b0000000000000011 4
b0000000000000011 5
#250000000
0!
0&
0-
03
#275000000
1!
b0000000000000011 %
1&
b0000000000000011 )
b0000000000000011 *
1-
b0000000000000011 0
b0000000000000011 1
b0000000000000011 2
13
#300000000
0!
0&
0-
03
#325000000
1!
1&
b0000000000000100 +
b0000000000000100 ,
1-
13
b0000000000000100 4
b0000000000000100 5
#350000000
0!
0&
0-
03
#375000000
1!
b0000000000000100 %
1&
b0000000000000100 )
b0000000000000100 *
1-
b0000000000000100 0
b0000000000000100 1
b0000000000000100 2
13
#400000000
0!
0&
0-
03
#425000000
1!
1&
b0000000000000101 +
b0000000000000101 ,
1-
13
b0000000000000101 4
b0000000000000101 5
#450000000
0!
0&
0-
03
#475000000
1!
b0000000000000101 %
1&
b0000000000000101 )
b0000000000000101 *
1-
b0000000000000101 0
b0000000000000101 1
b0000000000000101 2
13
#500000000
0!
0&
0-
03
#525000000
1!
1&
b0000000000000110 +
b0000000000000110 ,
1-
13
b0000000000000110 4
b0000000000000110 5
#550000000
0!
0&
0-
03
#575000000
1!
b0000000000000110 %
1&
b0000000000000110 )
b0000000000000110 *
1-
b0000000000000110 0
b0000000000000110 1
b0000000000000110 2
13
#600000000
0!
0&
0-
03
#625000000
1!
1&
b0000000000000111 +
b0000000000000111 ,
1-
13
b0000000000000111 4
b0000000000000111 5
#650000000
0!
0&
0-
03
#675000000
1!
b0000000000000111 %
1&
b0000000000000111 )
b0000000000000111 *
1-
b0000000000000111 0
b0000000000000111 1
b0000000000000111 2
13
#700000000
0!
0&
0-
03
#725000000
1!
1&
b0000000000001000 +
b0000000000001000 ,
1-
13
b0000000000001000 4
b0000000000001000 5
#750000000
0!
0&
0-
03
#775000000
1!
b0000000000001000 %
1&
b0000000000001000 )
b0000000000001000 *
1-
b0000000000001000 0
b0000000000001000 1
b0000000000001000 2
13
#800000000
0!
0&
0-
03
#825000000
1!
1&
b0000000000001001 +
b0000000000001001 ,
1-
13
b0000000000001001 4
b0000000000001001 5
#850000000
0!
0&
0-
03
#875000000
1!
b0000000000001001 %
1&
b0000000000001001 )
b0000000000001001 *
1-
b0000000000001001 0
b0000000000001001 1
b0000000000001001 2
13
#900000000
0!
0&
0-
03
#925000000
1!
1&
b0000000000001010 +
b0000000000001010 ,
1-
13
b0000000000001010 4
b0000000000001010 5
#950000000
0!
0&
0-
03
#975000000
1!
b0000000000001010 %
1&
b0000000000001010 )
b0000000000001010 *
1-
b0000000000001010 0
b0000000000001010 1
b0000000000001010 2
13
#1000000000
0!
1#
0&
0-
03
#1025000000
1!
1&
b0000000000001011 +
b0000000000001011 ,
1-
13
b0000000000001011 4
b0000000000001011 5
