microProcessador/rom.vhd
library IEEE;
use IEEE.std_logic_1164.all;
use IEEE.numeric_std.all;

entity rom is
    port(
        clk: in std_logic;
        address: in unsigned(15 downto 0);
        data_out: out unsigned(19 downto 0)
    );
end entity rom;

architecture rtl of rom is
    type mem is array (0 to 65535) of unsigned(19 downto 0);
    constant data_rom: mem := (
        0 => "00000101010101010101",
        1 => "00001010101010101010",
        2 => "00001100110011001100",
        3 => "00000011001100110011",
        others => (others => '0')
        );
begin
    process(clk)
    begin
        if (rising_edge(clk)) then
            data_out <= data_rom(to_integer(address));
        end if;
    end process;
end architecture rtl;

microProcessador/count_one.vhd
library IEEE;
use IEEE.std_logic_1164.all;
use IEEE.numeric_std.all;

entity count_one is
   port
   (
      data_pc:  in unsigned (15 downto 0);
      clk:      in std_logic;
      data_out: out unsigned (15 downto 0)
   );
end entity count_one;

architecture rtl of count_one is
   signal counting: unsigned (15 downto 0);
begin
   process(clk)
   begin
      if rising_edge(clk) then
         counting <= data_pc + "0000000000000001";
      end if;
   end process;

data_out <= counting;

end architecture rtl;

microProcessador/program_counter.vhd
library IEEE;
use IEEE.std_logic_1164.all;
use IEEE.numeric_std.all;

entity program_counter is
   port
   (
      data_in:                   in unsigned (15 downto 0);
      clk, write_en, reset:      in std_logic;
      data_out:                  out unsigned (15 downto 0)
   );
end entity program_counter;

architecture rtl of program_counter is
   signal data_sig : unsigned (15 downto 0);
   
begin
   
   process(clk, reset, write_en)
   begin
       if reset='1' then 
           data_sig <= "0000000000000000";
       elsif write_en='1' then
           if rising_edge(clk) then
               data_sig <= data_in;
           end if;
       end if;
   end process;
   
   data_out <= data_sig;
end architecture rtl;

microProcessador/pc_count_one.vhd
library IEEE;
use IEEE.std_logic_1164.all;
use IEEE.numeric_std.all;

entity pc_count_one is
    port (
        clk      : in std_logic;
        write_en : in std_logic;
        reset    : in std_logic;
        output_pc: out unsigned (15 downto 0)
    );
end entity;

architecture rtl of pc_count_one is
    component program_counter is
        port
        (
            data_in:                   in unsigned (15 downto 0);
            clk, write_en, reset:      in std_logic;
            data_out:                  out unsigned (15 downto 0)
        );
    end component;

    component count_one is
        port
        (
            data_pc:  in unsigned (15 downto 0);
            clk:      in std_logic;
            data_out: out unsigned (15 downto 0)
        );
    end component;

    signal data_out_pc_sig, data_out_count_sig: unsigned (15 downto 0);

begin

    pc: program_counter port map (data_in => data_out_count_sig, clk => clk, write_en => write_en, reset => reset, data_out => data_out_pc_sig);
    count: count_one port map (data_pc => data_out_pc_sig, clk => clk, data_out => data_out_count_sig);

    output_pc <= data_out_pc_sig;

end architecture rtl;

microProcessador/pc_rom.vhd
library IEEE;
use IEEE.std_logic_1164.all;
use IEEE.numeric_std.all;

entity pc_rom is
    port
    (
        clk, write_en, reset : in std_logic;
        data_out_rom         : out unsigned (19 downto 0)
    );
end entity pc_rom;

architecture rtl of pc_rom is
    component pc_count_one is
        port
        (
            clk      : in std_logic;
            write_en : in std_logic;
            reset    : in std_logic;
            output_pc: out unsigned (15 downto 0)
        );
    end component;

    component rom is
        port
        (
            clk: in std_logic;
            address: in unsigned(15 downto 0);
            data_out: out unsigned(19 downto 0)
        );
    end component;

    signal output_pc_sig: unsigned (15 downto 0);

    begin
        pc: pc_count_one port map(clk => clk, write_en => write_en, reset => reset, output_pc => output_pc_sig);
        read_only_memory: rom port map(clk => clk, address => output_pc_sig, data_out => data_out_rom);

end architecture rtl;

microProcessador/pc_rom_testbench.vhd
library IEEE;
use IEEE.std_logic_1164.all;
use IEEE.numeric_std.all;

entity pc_rom_testbench is
end entity;

architecture rtl of pc_rom_testbench is
    component pc_rom is
        port
        (
            clk, write_en, reset : in std_logic;
            data_out_rom         : out unsigned (19 downto 0)
        );
    end component;

    signal clk, write_en: std_logic;
    signal finish, reset: std_logic;
    signal data_out_rom : unsigned (19 downto 0); 
    constant time_period: time := 50 ns;
    
    begin
    uut: pc_rom port map
    (
        clk       => clk,
        write_en  => write_en,
        reset     => reset,
        data_out_rom => data_out_rom
    );
    
    reset_global:
    process
    begin
        reset <= '1';
        wait for time_period;
        reset <= '0';
        wait;
    end process;
    
    simulation_time:
    process
    begin
        wait for 1000 ns;
            finish <= '1';
        wait;
    end process;
    
    time_clk:
    process
    begin
        while finish /= '1' loop
            clk <= '0';
            wait for time_period/2;
            clk <= '1';
            wait for time_period/2;
        end loop;
        wait;
    end process;

    write_en_process:
    process
    begin
        write_en <= '1';
        wait;
    end process;

    process
    begin
        wait for time_period; -- visualiza o soma 1 a cada 2 clocks
        wait for time_period;
        wait for time_period;
        wait for time_period;
        wait for time_period;
        wait for time_period;
        wait for time_period;
        wait for time_period;
        wait for time_period;
        wait;
    end process;
end architecture rtl;

microProcessador/pc_rom_testbench.vcd
$date
  Wed Oct 19 23:06:32 2022
$end
$version
  GHDL v0
$end
$timescale
  1 fs
$end
$scope module standard $end
$upscope $end
$scope module textio $end
$upscope $end
$scope module std_logic_1164 $end
$upscope $end
$scope module numeric_std $end
$upscope $end
$scope module pc_rom_testbench $end
$var reg 1 ! clk $end
$var reg 1 " write_en $end
$var reg 1 # finish $end
$var reg 1 $ reset $end
$var reg 20 % data_out_rom[19:0] $end
$scope module uut $end
$var reg 1 & clk $end
$var reg 1 ' write_en $end
$var reg 1 ( reset $end
$var reg 20 ) data_out_rom[19:0] $end
$var reg 16 * output_pc_sig[15:0] $end
$scope module pc $end
$var reg 1 + clk $end
$var reg 1 , write_en $end
$var reg 1 - reset $end
$var reg 16 . output_pc[15:0] $end
$var reg 16 / data_out_pc_sig[15:0] $end
$var reg 16 0 data_out_count_sig[15:0] $end
$scope module pc $end
$var reg 16 1 data_in[15:0] $end
$var reg 1 2 clk $end
$var reg 1 3 write_en $end
$var reg 1 4 reset $end
$var reg 16 5 data_out[15:0] $end
$var reg 16 6 data_sig[15:0] $end
$upscope $end
$scope module count $end
$var reg 16 7 data_pc[15:0] $end
$var reg 1 8 clk $end
$var reg 16 9 data_out[15:0] $end
$var reg 16 : counting[15:0] $end
$upscope $end
$upscope $end
$scope module read_only_memory $end
$var reg 1 ; clk $end
$var reg 16 < address[15:0] $end
$var reg 20 = data_out[19:0] $end
$upscope $end
$upscope $end
$upscope $end
$enddefinitions $end
#0
0!
1"
U#
1$
bUUUUUUUUUUUUUUUUUUUU %
0&
1'
1(
bUUUUUUUUUUUUUUUUUUUU )
b0000000000000000 *
0+
1,
1-
b0000000000000000 .
b0000000000000000 /
bUUUUUUUUUUUUUUUU 0
bUUUUUUUUUUUUUUUU 1
02
13
14
b0000000000000000 5
b0000000000000000 6
b0000000000000000 7
08
bUUUUUUUUUUUUUUUU 9
bUUUUUUUUUUUUUUUU :
0;
b0000000000000000 <
bUUUUUUUUUUUUUUUUUUUU =
#25000000
1!
b00000101010101010101 %
1&
b00000101010101010101 )
1+
b0000000000000001 0
b0000000000000001 1
12
18
b0000000000000001 9
b0000000000000001 :
1;
b00000101010101010101 =
#50000000
0!
0$
0&
0(
0+
0-
02
04
08
0;
#75000000
1!
1&
b0000000000000001 *
1+
b0000000000000001 .
b0000000000000001 /
12
b0000000000000001 5
b0000000000000001 6
b0000000000000001 7
18
1;
b0000000000000001 <
#100000000
0!
0&
0+
02
08
0;
#125000000
1!
b00001010101010101010 %
1&
b00001010101010101010 )
1+
b0000000000000010 0
b0000000000000010 1
12
18
b0000000000000010 9
b0000000000000010 :
1;
b00001010101010101010 =
#150000000
0!
0&
0+
02
08
0;
#175000000
1!
1&
b0000000000000010 *
1+
b0000000000000010 .
b0000000000000010 /
12
b0000000000000010 5
b0000000000000010 6
b0000000000000010 7
18
1;
b0000000000000010 <
#200000000
0!
0&
0+
02
08
0;
#225000000
1!
b00001100110011001100 %
1&
b00001100110011001100 )
1+
b0000000000000011 0
b0000000000000011 1
12
18
b0000000000000011 9
b0000000000000011 :
1;
b00001100110011001100 =
#250000000
0!
0&
0+
02
08
0;
#275000000
1!
1&
b0000000000000011 *
1+
b0000000000000011 .
b0000000000000011 /
12
b0000000000000011 5
b0000000000000011 6
b0000000000000011 7
18
1;
b0000000000000011 <
#300000000
0!
0&
0+
02
08
0;
#325000000
1!
b00000011001100110011 %
1&
b00000011001100110011 )
1+
b0000000000000100 0
b0000000000000100 1
12
18
b0000000000000100 9
b0000000000000100 :
1;
b00000011001100110011 =
#350000000
0!
0&
0+
02
08
0;
#375000000
1!
1&
b0000000000000100 *
1+
b0000000000000100 .
b0000000000000100 /
12
b0000000000000100 5
b0000000000000100 6
b0000000000000100 7
18
1;
b0000000000000100 <
#400000000
0!
0&
0+
02
08
0;
#425000000
1!
b00000000000000000000 %
1&
b00000000000000000000 )
1+
b0000000000000101 0
b0000000000000101 1
12
18
b0000000000000101 9
b0000000000000101 :
1;
b00000000000000000000 =
#450000000
0!
0&
0+
02
08
0;
#475000000
1!
1&
b0000000000000101 *
1+
b0000000000000101 .
b0000000000000101 /
12
b0000000000000101 5
b0000000000000101 6
b0000000000000101 7
18
1;
b0000000000000101 <
#500000000
0!
0&
0+
02
08
0;
#525000000
1!
1&
1+
b0000000000000110 0
b0000000000000110 1
12
18
b0000000000000110 9
b0000000000000110 :
1;
#550000000
0!
0&
0+
02
08
0;
#575000000
1!
1&
b0000000000000110 *
1+
b0000000000000110 .
b0000000000000110 /
12
b0000000000000110 5
b0000000000000110 6
b0000000000000110 7
18
1;
b0000000000000110 <
#600000000
0!
0&
0+
02
08
0;
#625000000
1!
1&
1+
b0000000000000111 0
b0000000000000111 1
12
18
b0000000000000111 9
b0000000000000111 :
1;
#650000000
0!
0&
0+
02
08
0;
#675000000
1!
1&
b0000000000000111 *
1+
b0000000000000111 .
b0000000000000111 /
12
b0000000000000111 5
b0000000000000111 6
b0000000000000111 7
18
1;
b0000000000000111 <
#700000000
0!
0&
0+
02
08
0;
#725000000
1!
1&
1+
b0000000000001000 0
b0000000000001000 1
12
18
b0000000000001000 9
b0000000000001000 :
1;
#750000000
0!
0&
0+
02
08
0;
#775000000
1!
1&
b0000000000001000 *
1+
b0000000000001000 .
b0000000000001000 /
12
b0000000000001000 5
b0000000000001000 6
b0000000000001000 7
18
1;
b0000000000001000 <
#800000000
0!
0&
0+
02
08
0;
#825000000
1!
1&
1+
b0000000000001001 0
b0000000000001001 1
12
18
b0000000000001001 9
b0000000000001001 :
1;
#850000000
0!
0&
0+
02
08
0;
#875000000
1!
1&
b0000000000001001 *
1+
b0000000000001001 .
b0000000000001001 /
12
b0000000000001001 5
b0000000000001001 6
b0000000000001001 7
18
1;
b0000000000001001 <
#900000000
0!
0&
0+
02
08
0;
#925000000
1!
1&
1+
b0000000000001010 0
b0000000000001010 1
12
18
b0000000000001010 9
b0000000000001010 :
1;
#950000000
0!
0&
0+
02
08
0;
#975000000
1!
1&
b0000000000001010 *
1+
b0000000000001010 .
b0000000000001010 /
12
b0000000000001010 5
b0000000000001010 6
b0000000000001010 7
18
1;
b0000000000001010 <
#1000000000
0!
1#
0&
0+
02
08
0;
#1025000000
1!
1&
1+
b0000000000001011 0
b0000000000001011 1
12
18
b0000000000001011 9
b0000000000001011 :
1;
