microProcessador/reg_16_bits.vhd
library IEEE;
use IEEE.std_logic_1164.all;
use IEEE.numeric_std.all;

entity reg_16_bits is
    port
    (
        data_in:              in unsigned (15 downto 0);
        clk, reset, write_en: in std_logic;
        data_out:             out unsigned (15 downto 0)  
    );
end entity reg_16_bits;

architecture rtl of reg_16_bits is
    signal registring: unsigned (15 downto 0);
begin
    
    process(clk, reset, write_en)
    begin
        if reset='1' then 
            registring <= "0000000000000000";
        elsif write_en='1' then
            if rising_edge(clk) then
                registring <= data_in;
            end if;
        end if;
    end process;
    
    data_out <= registring;
end architecture rtl;

microProcessador/reg_bank.vhd
-- 2 barramentos selec para saber quais registradores serão lidos
-- barramento para o valor a ser escrito
-- barramento selec para escolher qual registrador será escrito
-- write_en 
-- clk
-- reset
-- 2 barramentos de saída com os dados dos registradores lidos

library IEEE;
use IEEE.std_logic_1164.all;
use IEEE.numeric_std.all;

entity reg_bank is
    port
    (
        selec_reg_a, selec_reg_b: in unsigned (2 downto 0);
        selec_reg_write:          in unsigned (2 downto 0);
        data_in:                  in unsigned (15 downto 0);
        write_en, clk, reset:     in std_logic;
        reg_data_a, reg_data_b:   out unsigned (15 downto 0)
    );
end entity;

architecture rtl of reg_bank is
    component reg_16_bits is
        port
        (
            data_in  : IN unsigned (15 downto 0);
            clk      : IN std_logic ;
            reset    : IN std_logic ;
            write_en : IN std_logic ;
            data_out : OUT unsigned (15 downto 0)
        );
    end component;

    signal data_out_0, data_out_1, data_out_2, data_out_3, data_out_4, data_out_5, data_out_6, data_out_7: unsigned (15 downto 0);
    signal write_en_0, write_en_1, write_en_2, write_en_3, write_en_4, write_en_5, write_en_6, write_en_7: std_logic;
    
begin
    reg_0: reg_16_bits port map(data_in=>data_in, clk=>clk, reset=>reset, write_en=>write_en_0, data_out=>data_out_0);
    reg_1: reg_16_bits port map(data_in=>data_in, clk=>clk, reset=>reset, write_en=>write_en_1, data_out=>data_out_1);
    reg_2: reg_16_bits port map(data_in=>data_in, clk=>clk, reset=>reset, write_en=>write_en_2, data_out=>data_out_2);
    reg_3: reg_16_bits port map(data_in=>data_in, clk=>clk, reset=>reset, write_en=>write_en_3, data_out=>data_out_3);
    reg_4: reg_16_bits port map(data_in=>data_in, clk=>clk, reset=>reset, write_en=>write_en_4, data_out=>data_out_4);
    reg_5: reg_16_bits port map(data_in=>data_in, clk=>clk, reset=>reset, write_en=>write_en_5, data_out=>data_out_5);
    reg_6: reg_16_bits port map(data_in=>data_in, clk=>clk, reset=>reset, write_en=>write_en_6, data_out=>data_out_6);
    reg_7: reg_16_bits port map(data_in=>data_in, clk=>clk, reset=>reset, write_en=>write_en_7, data_out=>data_out_7);
    
    reg_data_a <= data_out_0 when selec_reg_a = "000" else
                  data_out_1 when selec_reg_a = "001" else
                  data_out_2 when selec_reg_a = "010" else
                  data_out_3 when selec_reg_a = "011" else
                  data_out_4 when selec_reg_a = "100" else
                  data_out_5 when selec_reg_a = "101" else
                  data_out_6 when selec_reg_a = "110" else
                  data_out_7 when selec_reg_a = "111" else
                  "0000000000000000";
                
    reg_data_b <= data_out_0 when selec_reg_b = "000" else
                  data_out_1 when selec_reg_b = "001" else
                  data_out_2 when selec_reg_b = "010" else
                  data_out_3 when selec_reg_b = "011" else
                  data_out_4 when selec_reg_b = "100" else
                  data_out_5 when selec_reg_b = "101" else
                  data_out_6 when selec_reg_b = "110" else
                  data_out_7 when selec_reg_b = "111" else
                  "0000000000000000";

    write_en_0 <= '0'; -- Allways connected to GND
    write_en_1 <= write_en when selec_reg_write = "001" else '0';
    write_en_2 <= write_en when selec_reg_write = "010" else '0';
    write_en_3 <= write_en when selec_reg_write = "011" else '0';
    write_en_4 <= write_en when selec_reg_write = "100" else '0';
    write_en_5 <= write_en when selec_reg_write = "101" else '0';
    write_en_6 <= write_en when selec_reg_write = "110" else '0';
    write_en_7 <= write_en when selec_reg_write = "111" else '0';

    
end architecture rtl;

microProcessador/reg_bank_testbench.vhd
library IEEE;
use IEEE.std_logic_1164.all;
use IEEE.numeric_std.all;

entity reg_bank_testbench is
end entity reg_bank_testbench;

architecture rtl of reg_bank_testbench is
    component reg_bank is
        port
        (
            selec_reg_a     : IN unsigned (2 downto 0);
            selec_reg_b     : IN unsigned (2 downto 0);
            selec_reg_write : IN unsigned (2 downto 0);
            data_in         : IN unsigned (15 downto 0);
            write_en        : IN std_logic ;
            clk             : IN std_logic ;
            reset           : IN std_logic ;
            reg_data_a      : OUT unsigned (15 downto 0);
            reg_data_b      : OUT unsigned (15 downto 0)
        );
    end component;
    
    constant time_period: time := 100 fs;
    
    signal selec_reg_a, selec_reg_b, selec_reg_write: unsigned (2 downto 0);
    signal data_in, reg_data_a, reg_data_b: unsigned (15 downto 0);
    signal write_en, clk, reset, finished: std_logic;
    
begin
    uut: reg_bank port map(
        selec_reg_a     => selec_reg_a    , 
        selec_reg_b     => selec_reg_b    ,
        selec_reg_write => selec_reg_write,
        data_in         => data_in        ,
        write_en        => write_en       ,
        clk             => clk            ,
        reset           => reset          ,
        reg_data_a      => reg_data_a     ,
        reg_data_b      => reg_data_b
    );

    reset_global: process
    begin
        reset <= '1';
        wait for time_period;
        reset <= '0';
        wait;
    end process;
    
    simulation_time: process
    begin
        wait for 1 ns;
        finished <= '1';
        wait;
    end process;
    
    clock_behavior: process
    begin
        while finished /= '1' loop
            clk <= '0';
            wait for time_period/2;
            clk <= '1';
            wait for time_period/2;
        end loop;
        wait;
    end process;
    
    process
    begin
        wait for 2*time_period;
        selec_reg_a <= "000";
        selec_reg_b <= "100";
        selec_reg_write <= "000";
        data_in <= "0000000000000000";
        write_en <= '0';
        wait for 2*time_period;
        selec_reg_a <= "001";
        selec_reg_b <= "100";
        selec_reg_write <= "001";
        data_in <= "0000000000001111";
        write_en <= '1';
        wait for 2*time_period;
        selec_reg_a <= "001";
        selec_reg_b <= "001";
        selec_reg_write <= "000";
        data_in <= "0000000000000000";
        write_en <= '1';
        wait for 2*time_period;
        selec_reg_a <= "000";
        selec_reg_b <= "001";
        selec_reg_write <= "000";
        data_in <= "0000000000000000";
        write_en <= '1';
        wait for 2*time_period;
        selec_reg_a <= "111";
        selec_reg_b <= "101";
        selec_reg_write <= "111";
        data_in <= "0001000010100000";
        write_en <= '1';
        wait for 2*time_period;
        selec_reg_a <= "011";
        selec_reg_b <= "100";
        selec_reg_write <= "101";
        data_in <= "0000000001010101";
        write_en <= '1';
        wait for 2*time_period;
        selec_reg_a <= "000";
        selec_reg_b <= "101";
        selec_reg_write <= "100";
        data_in <= "1111000011011010";
        write_en <= '1';
        wait for 2*time_period;
        selec_reg_a <= "010";
        selec_reg_b <= "100";
        selec_reg_write <= "110";
        data_in <= "1111000011011010";
        write_en <= '1';
        wait for 2*time_period;
        selec_reg_a <= "110";
        selec_reg_b <= "100";
        selec_reg_write <= "011";
        data_in <= "1101101011010000";
        write_en <= '1';
        wait for 2*time_period;
        selec_reg_a <= "010";
        selec_reg_b <= "100";
        selec_reg_write <= "010";
        data_in <= "1101101011010001";
        write_en <= '1';
        wait for 2*time_period;
        write_en <= '0';
        wait;
    end process;
end architecture rtl;

microProcessador/reg_bank_testbench.vcd
$date
  Thu Sep 29 18:49:29 2022
$end
$version
  GHDL v0
$end
$timescale
  1 fs
$end
$scope module standard $end
$upscope $end
$scope module textio $end
$upscope $end
$scope module std_logic_1164 $end
$upscope $end
$scope module numeric_std $end
$upscope $end
$scope module reg_bank_testbench $end
$var reg 3 ! selec_reg_a[2:0] $end
$var reg 3 " selec_reg_b[2:0] $end
$var reg 3 # selec_reg_write[2:0] $end
$var reg 16 $ data_in[15:0] $end
$var reg 16 % reg_data_a[15:0] $end
$var reg 16 & reg_data_b[15:0] $end
$var reg 1 ' write_en $end
$var reg 1 ( clk $end
$var reg 1 ) reset $end
$var reg 1 * finished $end
$scope module uut $end
$var reg 3 + selec_reg_a[2:0] $end
$var reg 3 , selec_reg_b[2:0] $end
$var reg 3 - selec_reg_write[2:0] $end
$var reg 16 . data_in[15:0] $end
$var reg 1 / write_en $end
$var reg 1 0 clk $end
$var reg 1 1 reset $end
$var reg 16 2 reg_data_a[15:0] $end
$var reg 16 3 reg_data_b[15:0] $end
$var reg 16 4 data_out_0[15:0] $end
$var reg 16 5 data_out_1[15:0] $end
$var reg 16 6 data_out_2[15:0] $end
$var reg 16 7 data_out_3[15:0] $end
$var reg 16 8 data_out_4[15:0] $end
$var reg 16 9 data_out_5[15:0] $end
$var reg 16 : data_out_6[15:0] $end
$var reg 16 ; data_out_7[15:0] $end
$var reg 1 < write_en_0 $end
$var reg 1 = write_en_1 $end
$var reg 1 > write_en_2 $end
$var reg 1 ? write_en_3 $end
$var reg 1 @ write_en_4 $end
$var reg 1 A write_en_5 $end
$var reg 1 B write_en_6 $end
$var reg 1 C write_en_7 $end
$scope module reg_0 $end
$var reg 16 D data_in[15:0] $end
$var reg 1 E clk $end
$var reg 1 F reset $end
$var reg 1 G write_en $end
$var reg 16 H data_out[15:0] $end
$var reg 16 I registring[15:0] $end
$upscope $end
$scope module reg_1 $end
$var reg 16 J data_in[15:0] $end
$var reg 1 K clk $end
$var reg 1 L reset $end
$var reg 1 M write_en $end
$var reg 16 N data_out[15:0] $end
$var reg 16 O registring[15:0] $end
$upscope $end
$scope module reg_2 $end
$var reg 16 P data_in[15:0] $end
$var reg 1 Q clk $end
$var reg 1 R reset $end
$var reg 1 S write_en $end
$var reg 16 T data_out[15:0] $end
$var reg 16 U registring[15:0] $end
$upscope $end
$scope module reg_3 $end
$var reg 16 V data_in[15:0] $end
$var reg 1 W clk $end
$var reg 1 X reset $end
$var reg 1 Y write_en $end
$var reg 16 Z data_out[15:0] $end
$var reg 16 [ registring[15:0] $end
$upscope $end
$scope module reg_4 $end
$var reg 16 \ data_in[15:0] $end
$var reg 1 ] clk $end
$var reg 1 ^ reset $end
$var reg 1 _ write_en $end
$var reg 16 ` data_out[15:0] $end
$var reg 16 a registring[15:0] $end
$upscope $end
$scope module reg_5 $end
$var reg 16 b data_in[15:0] $end
$var reg 1 c clk $end
$var reg 1 d reset $end
$var reg 1 e write_en $end
$var reg 16 f data_out[15:0] $end
$var reg 16 g registring[15:0] $end
$upscope $end
$scope module reg_6 $end
$var reg 16 h data_in[15:0] $end
$var reg 1 i clk $end
$var reg 1 j reset $end
$var reg 1 k write_en $end
$var reg 16 l data_out[15:0] $end
$var reg 16 m registring[15:0] $end
$upscope $end
$scope module reg_7 $end
$var reg 16 n data_in[15:0] $end
$var reg 1 o clk $end
$var reg 1 p reset $end
$var reg 1 q write_en $end
$var reg 16 r data_out[15:0] $end
$var reg 16 s registring[15:0] $end
$upscope $end
$upscope $end
$upscope $end
$enddefinitions $end
#0
bUUU !
bUUU "
bUUU #
bUUUUUUUUUUUUUUUU $
b0000000000000000 %
b0000000000000000 &
U'
0(
1)
U*
bUUU +
bUUU ,
bUUU -
bUUUUUUUUUUUUUUUU .
U/
00
11
b0000000000000000 2
b0000000000000000 3
b0000000000000000 4
b0000000000000000 5
b0000000000000000 6
b0000000000000000 7
b0000000000000000 8
b0000000000000000 9
b0000000000000000 :
b0000000000000000 ;
0<
0=
0>
0?
0@
0A
0B
0C
bUUUUUUUUUUUUUUUU D
0E
1F
0G
b0000000000000000 H
b0000000000000000 I
bUUUUUUUUUUUUUUUU J
0K
1L
0M
b0000000000000000 N
b0000000000000000 O
bUUUUUUUUUUUUUUUU P
0Q
1R
0S
b0000000000000000 T
b0000000000000000 U
bUUUUUUUUUUUUUUUU V
0W
1X
0Y
b0000000000000000 Z
b0000000000000000 [
bUUUUUUUUUUUUUUUU \
0]
1^
0_
b0000000000000000 `
b0000000000000000 a
bUUUUUUUUUUUUUUUU b
0c
1d
0e
b0000000000000000 f
b0000000000000000 g
bUUUUUUUUUUUUUUUU h
0i
1j
0k
b0000000000000000 l
b0000000000000000 m
bUUUUUUUUUUUUUUUU n
0o
1p
0q
b0000000000000000 r
b0000000000000000 s
#50
1(
10
1E
1K
1Q
1W
1]
1c
1i
1o
#100
0(
0)
00
01
0E
0F
0K
0L
0Q
0R
0W
0X
0]
0^
0c
0d
0i
0j
0o
0p
#150
1(
10
1E
1K
1Q
1W
1]
1c
1i
1o
#200
b000 !
b100 "
b000 #
b0000000000000000 $
0'
0(
b000 +
b100 ,
b000 -
b0000000000000000 .
0/
00
b0000000000000000 D
0E
b0000000000000000 J
0K
b0000000000000000 P
0Q
b0000000000000000 V
0W
b0000000000000000 \
0]
b0000000000000000 b
0c
b0000000000000000 h
0i
b0000000000000000 n
0o
#250
1(
10
1E
1K
1Q
1W
1]
1c
1i
1o
#300
0(
00
0E
0K
0Q
0W
0]
0c
0i
0o
#350
1(
10
1E
1K
1Q
1W
1]
1c
1i
1o
#400
b001 !
b001 #
b0000000000001111 $
1'
0(
b001 +
b001 -
b0000000000001111 .
1/
00
1=
b0000000000001111 D
0E
b0000000000001111 J
0K
1M
b0000000000001111 P
0Q
b0000000000001111 V
0W
b0000000000001111 \
0]
b0000000000001111 b
0c
b0000000000001111 h
0i
b0000000000001111 n
0o
#450
b0000000000001111 %
1(
10
b0000000000001111 2
b0000000000001111 5
1E
1K
b0000000000001111 N
b0000000000001111 O
1Q
1W
1]
1c
1i
1o
#500
0(
00
0E
0K
0Q
0W
0]
0c
0i
0o
#550
1(
10
1E
1K
1Q
1W
1]
1c
1i
1o
#600
b001 "
b000 #
b0000000000000000 $
b0000000000001111 &
0(
b001 ,
b000 -
b0000000000000000 .
00
b0000000000001111 3
0=
b0000000000000000 D
0E
b0000000000000000 J
0K
0M
b0000000000000000 P
0Q
b0000000000000000 V
0W
b0000000000000000 \
0]
b0000000000000000 b
0c
b0000000000000000 h
0i
b0000000000000000 n
0o
#650
1(
10
1E
1K
1Q
1W
1]
1c
1i
1o
#700
0(
00
0E
0K
0Q
0W
0]
0c
0i
0o
#750
1(
10
1E
1K
1Q
1W
1]
1c
1i
1o
#800
b000 !
b0000000000000000 %
0(
b000 +
00
b0000000000000000 2
0E
0K
0Q
0W
0]
0c
0i
0o
#850
1(
10
1E
1K
1Q
1W
1]
1c
1i
1o
#900
0(
00
0E
0K
0Q
0W
0]
0c
0i
0o
#950
1(
10
1E
1K
1Q
1W
1]
1c
1i
1o
#1000
b111 !
b101 "
b111 #
b0001000010100000 $
b0000000000000000 &
0(
b111 +
b101 ,
b111 -
b0001000010100000 .
00
b0000000000000000 3
1C
b0001000010100000 D
0E
b0001000010100000 J
0K
b0001000010100000 P
0Q
b0001000010100000 V
0W
b0001000010100000 \
0]
b0001000010100000 b
0c
b0001000010100000 h
0i
b0001000010100000 n
0o
1q
#1050
b0001000010100000 %
1(
10
b0001000010100000 2
b0001000010100000 ;
1E
1K
1Q
1W
1]
1c
1i
1o
b0001000010100000 r
b0001000010100000 s
#1100
0(
00
0E
0K
0Q
0W
0]
0c
0i
0o
#1150
1(
10
1E
1K
1Q
1W
1]
1c
1i
1o
#1200
b011 !
b100 "
b101 #
b0000000001010101 $
b0000000000000000 %
0(
b011 +
b100 ,
b101 -
b0000000001010101 .
00
b0000000000000000 2
1A
0C
b0000000001010101 D
0E
b0000000001010101 J
0K
b0000000001010101 P
0Q
b0000000001010101 V
0W
b0000000001010101 \
0]
b0000000001010101 b
0c
1e
b0000000001010101 h
0i
b0000000001010101 n
0o
0q
#1250
1(
10
b0000000001010101 9
1E
1K
1Q
1W
1]
1c
b0000000001010101 f
b0000000001010101 g
1i
1o
#1300
0(
00
0E
0K
0Q
0W
0]
0c
0i
0o
#1350
1(
10
1E
1K
1Q
1W
1]
1c
1i
1o
#1400
b000 !
b101 "
b100 #
b1111000011011010 $
b0000000001010101 &
0(
b000 +
b101 ,
b100 -
b1111000011011010 .
00
b0000000001010101 3
1@
0A
b1111000011011010 D
0E
b1111000011011010 J
0K
b1111000011011010 P
0Q
b1111000011011010 V
0W
b1111000011011010 \
0]
1_
b1111000011011010 b
0c
0e
b1111000011011010 h
0i
b1111000011011010 n
0o
#1450
1(
10
b1111000011011010 8
1E
1K
1Q
1W
1]
b1111000011011010 `
b1111000011011010 a
1c
1i
1o
#1500
0(
00
0E
0K
0Q
0W
0]
0c
0i
0o
#1550
1(
10
1E
1K
1Q
1W
1]
1c
1i
1o
#1600
b010 !
b100 "
b110 #
b1111000011011010 &
0(
b010 +
b100 ,
b110 -
00
b1111000011011010 3
0@
1B
0E
0K
0Q
0W
0]
0_
0c
0i
1k
0o
#1650
1(
10
b1111000011011010 :
1E
1K
1Q
1W
1]
1c
1i
b1111000011011010 l
b1111000011011010 m
1o
#1700
0(
00
0E
0K
0Q
0W
0]
0c
0i
0o
#1750
1(
10
1E
1K
1Q
1W
1]
1c
1i
1o
#1800
b110 !
b011 #
b1101101011010000 $
b1111000011011010 %
0(
b110 +
b011 -
b1101101011010000 .
00
b1111000011011010 2
1?
0B
b1101101011010000 D
0E
b1101101011010000 J
0K
b1101101011010000 P
0Q
b1101101011010000 V
0W
1Y
b1101101011010000 \
0]
b1101101011010000 b
0c
b1101101011010000 h
0i
0k
b1101101011010000 n
0o
#1850
1(
10
b1101101011010000 7
1E
1K
1Q
1W
b1101101011010000 Z
b1101101011010000 [
1]
1c
1i
1o
#1900
0(
00
0E
0K
0Q
0W
0]
0c
0i
0o
#1950
1(
10
1E
1K
1Q
1W
1]
1c
1i
1o
#2000
b010 !
b010 #
b1101101011010001 $
b0000000000000000 %
0(
b010 +
b010 -
b1101101011010001 .
00
b0000000000000000 2
1>
0?
b1101101011010001 D
0E
b1101101011010001 J
0K
b1101101011010001 P
0Q
1S
b1101101011010001 V
0W
0Y
b1101101011010001 \
0]
b1101101011010001 b
0c
b1101101011010001 h
0i
b1101101011010001 n
0o
#2050
b1101101011010001 %
1(
10
b1101101011010001 2
b1101101011010001 6
1E
1K
1Q
b1101101011010001 T
b1101101011010001 U
1W
1]
1c
1i
1o
#2100
0(
00
0E
0K
0Q
0W
0]
0c
0i
0o
#2150
1(
10
1E
1K
1Q
1W
1]
1c
1i
1o
#2200
0'
0(
0/
00
0>
0E
0K
0Q
0S
0W
0]
0c
0i
0o
