microProcessador/state_machine.vhd
library ieee;
use ieee.std_logic_1164.all;
use ieee.numeric_std.all;

entity state_machine is
   port
   (
      clk, reset: in std_logic;
      output    : out std_logic
   );
end entity;

architecture rtl of state_machine is
signal state: std_logic;
begin
   process (clk, reset)
   begin
      if reset='1' then
         state <= '0';
      elsif rising_edge(clk) then
         state <= not state;
      end if;
   end process;
   output <= state;

end architecture;

microProcessador/state_machine_testbench.vhd
library ieee;
use ieee.std_logic_1164.all;
use ieee.numeric_std.all;

entity state_machine_testbench is
end entity;

architecture rtl of state_machine_testbench is
   component state_machine is
      port
      (
         clk, reset: in std_logic;
         output: out std_logic
      );
   end component;

   signal clk, output  : std_logic;
   signal finish, reset: std_logic;
   constant time_period: time := 50 ns;

begin
   uut: state_machine port map
   (
      clk => clk,
      reset => reset,
      output => output
   );

   reset_global:
   process
   begin
      reset <= '1';
      wait for time_period;
      reset <= '0';
      wait;
   end process;

   simulation_time:
   process
   begin
      wait for 1000 ns;
         finish <= '1';
      wait;
   end process;

   time_clk:
   process
   begin
      while finish /= '1' loop
         clk <= '0';
         wait for time_period/2;
         clk <= '1';
         wait for time_period/2;
      end loop;
      wait;
end process;

process
begin
   wait for 2*time_period; -- visualiza a alteração de estado a cada 2 clocks
   wait for 2*time_period;
   wait for 2*time_period;
   wait for 2*time_period;
   wait for 2*time_period;
   wait for 2*time_period;
   wait for 2*time_period;
   wait for 2*time_period;
   wait for 2*time_period;
   wait for 2*time_period;
   wait;
end process;
end architecture;

microProcessador/state_machine_testbench.vcd
$date
  Wed Oct 19 21:45:55 2022
$end
$version
  GHDL v0
$end
$timescale
  1 fs
$end
$scope module standard $end
$upscope $end
$scope module textio $end
$upscope $end
$scope module std_logic_1164 $end
$upscope $end
$scope module numeric_std $end
$upscope $end
$scope module state_machine_testbench $end
$var reg 1 ! clk $end
$var reg 1 " output $end
$var reg 1 # finish $end
$var reg 1 $ reset $end
$scope module uut $end
$var reg 1 % clk $end
$var reg 1 & reset $end
$var reg 1 ' output $end
$var reg 1 ( state $end
$upscope $end
$upscope $end
$enddefinitions $end
#0
0!
0"
0#
1$
0%
1&
0'
0(
#25000000
1!
1%
#50000000
0!
0$
0%
0&
#75000000
1!
1"
1%
1'
1(
#100000000
0!
0%
#125000000
1!
0"
1%
0'
0(
#150000000
0!
0%
#175000000
1!
1"
1%
1'
1(
#200000000
0!
0%
#225000000
1!
0"
1%
0'
0(
#250000000
0!
0%
#275000000
1!
1"
1%
1'
1(
#300000000
0!
0%
#325000000
1!
0"
1%
0'
0(
#350000000
0!
0%
#375000000
1!
1"
1%
1'
1(
#400000000
0!
0%
#425000000
1!
0"
1%
0'
0(
#450000000
0!
0%
#475000000
1!
1"
1%
1'
1(
#500000000
0!
0%
#525000000
1!
0"
1%
0'
0(
#550000000
0!
0%
#575000000
1!
1"
1%
1'
1(
#600000000
0!
0%
#625000000
1!
0"
1%
0'
0(
#650000000
0!
0%
#675000000
1!
1"
1%
1'
1(
#700000000
0!
0%
#725000000
1!
0"
1%
0'
0(
#750000000
0!
0%
#775000000
1!
1"
1%
1'
1(
#800000000
0!
0%
#825000000
1!
0"
1%
0'
0(
#850000000
0!
0%
#875000000
1!
1"
1%
1'
1(
#900000000
0!
0%
#925000000
1!
0"
1%
0'
0(
#950000000
0!
0%
#975000000
1!
1"
1%
1'
1(
#1000000000
0!
1#
0%
#1025000000
1!
0"
1%
0'
0(
