microProcessador/ula.vhd
library IEEE;
use IEEE.std_logic_1164.all;
use IEEE.numeric_std.all;

entity ula is
   port(
      a,b:             in  unsigned(15 downto 0);
      selec:           in  unsigned(1 downto 0);
      output:          out unsigned(15 downto 0);
      equal, greater_a, a_negative, b_negative: out std_logic
   );
end entity;

architecture rtl of ula is
   begin
      output <= a+b when selec="00"                            else
                a-b when selec="01"                            else
                a(15 downto 8) & b(7 downto 0) when selec="10" else -- Concatenates aMSB & bLSB
                b(15 downto 8) & a(7 downto 0) when selec="11" else -- Concatenates bMSB & aLSB
                "0000000000000000";

      equal <= '1' when a=b else
               '0';
      greater_a <= '1' when a>b else
                   '0';
                   
      a_negative <= a(15);
      b_negative <= b(15);
end architecture rtl;

microProcessador/ula_testbench.vhd
library IEEE;
use IEEE.std_logic_1164.all;
use IEEE.numeric_std.all;

entity ula_testbench is
end entity;

architecture rtl of ula_testbench is
    component ula is
        port
        (
            a          : IN unsigned (15 downto 0);
            b          : IN unsigned (15 downto 0);
            selec      : IN unsigned (1 downto 0);
            output     : OUT unsigned (15 downto 0);
            equal       : OUT std_logic ;
            greater_a  : OUT std_logic ;
            a_negative : OUT std_logic ;
            b_negative : OUT std_logic
        );
    end component;

    signal a, b, output: unsigned (15 downto 0);
    signal selec: unsigned(1 downto 0);
    signal equal, greater_a, a_negative, b_negative: std_logic;

begin
   uut: ula port map(
      a => a,
      b => b,
      selec => selec,
      output => output,
      equal => equal,
      greater_a => greater_a,
      a_negative => a_negative,
      b_negative => b_negative
   );

   process
   begin
      -- SOMA SUBTRAI -----------------------------
      a <= "0000000000000000";
      b <= "0000000000000000";
      selec <= "00";
      wait for 50 ns;
      a <= "0000000000000000";
      b <= "0000000000000000";
      selec <= "01";
      wait for 50 ns;
      -- a e b positivos soma
      a <= "0000000001000101";
      b <= "0000000110100100";
      selec <= "00";
      wait for 50 ns;
      -- a e b positivos subtrai
      a <= "0000000001000101";
      b <= "0000000110100100";
      selec <= "01";
      wait for 50 ns;
      -- a negativo b positivo soma
      a <= "1000000001000101";
      b <= "0000000110100100";
      selec <= "00";
      wait for 50 ns;
      -- a negativo b positivo subtrai
      a <= "1000000001000101";
      b <= "0000000110100100";
      selec <= "01";
      wait for 50 ns;
      -- a positivo b negativo soma
      a <= "0000000001000101";
      b <= "1000000110100100";
      selec <= "00";
      wait for 50 ns;
      -- a positivo b negativo subtrai
      a <= "0000000001000101";
      b <= "1000000110100100";
      selec <= "01";
      wait for 50 ns;
      -- a e b negativos soma
      a <= "1010010001100101";
      b <= "1100100110100100";
      selec <= "00";
      wait for 50 ns;
      -- a e b negativos subtrai
      a <= "1010010001100101";
      b <= "1100100110100100";
      selec <= "01";
      -- CONCATENATE aMSB&bLSB ------------------------------------
      wait for 50 ns;
      a <= "1111111111111111";
      b <= "0000000000000000";
      selec <= "10";
      wait for 50 ns;
      a <= "0000000000000000";
      b <= "1111111111111111";
      selec <= "10";
      -- CONCATENATE bMSB&aLSB--------------------------------
      wait for 50 ns;
      a <= "1111111111111111";
      b <= "0000000000000000";
      selec <= "11";
      wait for 50 ns;
      a <= "0000000000000000";
      b <= "1111111111111111";
      selec <= "11";
      wait for 50 ns;
      wait;
   end process;
end architecture rtl;

microProcessador/ula_testbench.vcd
$date
  Sat Sep 17 20:21:59 2022
$end
$version
  GHDL v0
$end
$timescale
  1 fs
$end
$scope module standard $end
$upscope $end
$scope module textio $end
$upscope $end
$scope module std_logic_1164 $end
$upscope $end
$scope module numeric_std $end
$upscope $end
$scope module ula_testbench $end
$var reg 16 ! a[15:0] $end
$var reg 16 " b[15:0] $end
$var reg 16 # output[15:0] $end
$var reg 2 $ selec[1:0] $end
$var reg 1 % equal $end
$var reg 1 & greater_a $end
$var reg 1 ' a_negative $end
$var reg 1 ( b_negative $end
$scope module uut $end
$var reg 16 ) a[15:0] $end
$var reg 16 * b[15:0] $end
$var reg 2 + selec[1:0] $end
$var reg 16 , output[15:0] $end
$var reg 1 - equal $end
$var reg 1 . greater_a $end
$var reg 1 / a_negative $end
$var reg 1 0 b_negative $end
$upscope $end
$upscope $end
$enddefinitions $end
#0
b0000000000000000 !
b0000000000000000 "
b0000000000000000 #
b00 $
1%
0&
0'
0(
b0000000000000000 )
b0000000000000000 *
b00 +
b0000000000000000 ,
1-
0.
0/
00
#50000000
b01 $
b01 +
#100000000
b0000000001000101 !
b0000000110100100 "
b0000000111101001 #
b00 $
0%
b0000000001000101 )
b0000000110100100 *
b00 +
b0000000111101001 ,
0-
#150000000
b1111111010100001 #
b01 $
b01 +
b1111111010100001 ,
#200000000
b1000000001000101 !
b1000000111101001 #
b00 $
1&
1'
b1000000001000101 )
b00 +
b1000000111101001 ,
1.
1/
#250000000
b0111111010100001 #
b01 $
b01 +
b0111111010100001 ,
#300000000
b0000000001000101 !
b1000000110100100 "
b1000000111101001 #
b00 $
0&
0'
1(
b0000000001000101 )
b1000000110100100 *
b00 +
b1000000111101001 ,
0.
0/
10
#350000000
b0111111010100001 #
b01 $
b01 +
b0111111010100001 ,
#400000000
b1010010001100101 !
b1100100110100100 "
b0110111000001001 #
b00 $
1'
b1010010001100101 )
b1100100110100100 *
b00 +
b0110111000001001 ,
1/
#450000000
b1101101011000001 #
b01 $
b01 +
b1101101011000001 ,
#500000000
b1111111111111111 !
b0000000000000000 "
b1111111100000000 #
b10 $
1&
0(
b1111111111111111 )
b0000000000000000 *
b10 +
b1111111100000000 ,
1.
00
#550000000
b0000000000000000 !
b1111111111111111 "
b0000000011111111 #
0&
0'
1(
b0000000000000000 )
b1111111111111111 *
b0000000011111111 ,
0.
0/
10
#600000000
b1111111111111111 !
b0000000000000000 "
b11 $
1&
1'
0(
b1111111111111111 )
b0000000000000000 *
b11 +
1.
1/
00
#650000000
b0000000000000000 !
b1111111111111111 "
b1111111100000000 #
0&
0'
1(
b0000000000000000 )
b1111111111111111 *
b1111111100000000 ,
0.
0/
10
