microProcessador/ula.vhd
library IEEE;
use IEEE.std_logic_1164.all;
use IEEE.numeric_std.all;

entity ula is
   port(
      a,b:             in  unsigned(15 downto 0);
      selec:           in  unsigned(1 downto 0);
      output:          out unsigned(15 downto 0);
      output2:         out unsigned(15 downto 0);
      equal, greater_a, a_negative, b_negative: out std_logic
   );
end entity;

architecture rtl of ula is
   begin
      output <= a+b when selec="00"                            else
                a-b when selec="01"                            else
                a(15 downto 8) & b(7 downto 0) when selec="10" else -- Concatenates aMSB & bLSB
                b(15 downto 8) & a(7 downto 0) when selec="11" else -- Concatenates bMSB & aLSB
                "0000000000000000";
    
      output2 <= output;

      equal <= '1' when a=b else
               '0';
      greater_a <= '1' when a>b else
                   '0';
                   
      a_negative <= a(15);
      b_negative <= b(15);
end architecture rtl;

microProcessador/reg_16_bits.vhd
library IEEE;
use IEEE.std_logic_1164.all;
use IEEE.numeric_std.all;

entity reg_16_bits is
    port
    (
        data_in:                 in unsigned (15 downto 0);
        clk, reset, write_en: in std_logic;
        data_out:             out unsigned (15 downto 0)  
    );
end entity reg_16_bits;

architecture rtl of reg_16_bits is
    signal registring: unsigned (15 downto 0);
begin
    
    process(clk, reset, write_en)
    begin
        if reset='1' then 
            registring <= "0000000000000000";
        elsif write_en='1' then
            if rising_edge(clk) then
                registring <= data_in;
            end if;
        end if;
    end process;
    
    data_out <= registring;
end architecture rtl;

microProcessador/reg_bank.vhd
-- 2 barramentos selec para saber quais registradores serão lidos
-- barramento para o valor a ser escrito
-- barramento selec para escolher qual registrador será escrito
-- write_en 
-- clk
-- reset
-- 2 barramentos de saída com os dados dos registradores lidos

library IEEE;
use IEEE.std_logic_1164.all;
use IEEE.numeric_std.all;

entity reg_bank is
    port
    (
        selec_reg_a, selec_reg_b: in unsigned (2 downto 0);
        selec_reg_write:          in unsigned (2 downto 0);
        data_in:                  in unsigned (15 downto 0);
        write_en, clk, reset:     in std_logic;
        reg_data_a, reg_data_b:   out unsigned (15 downto 0)
    );
end entity;

architecture rtl of reg_bank is
    component reg_16_bits is
        port
        (
            data_in  : IN unsigned (15 downto 0);
            clk      : IN std_logic ;
            reset    : IN std_logic ;
            write_en : IN std_logic ;
            data_out : OUT unsigned (15 downto 0)
        );
    end component;

    signal data_out_0, data_out_1, data_out_2, data_out_3, data_out_4, data_out_5, data_out_6, data_out_7: unsigned (15 downto 0);
    signal write_en_0, write_en_1, write_en_2, write_en_3, write_en_4, write_en_5, write_en_6, write_en_7: std_logic;
    
begin
    reg_0: reg_16_bits port map(data_in=>data_in, clk=>clk, reset=>reset, write_en=>write_en_0, data_out=>data_out_0);
    reg_1: reg_16_bits port map(data_in=>data_in, clk=>clk, reset=>reset, write_en=>write_en_1, data_out=>data_out_1);
    reg_2: reg_16_bits port map(data_in=>data_in, clk=>clk, reset=>reset, write_en=>write_en_2, data_out=>data_out_2);
    reg_3: reg_16_bits port map(data_in=>data_in, clk=>clk, reset=>reset, write_en=>write_en_3, data_out=>data_out_3);
    reg_4: reg_16_bits port map(data_in=>data_in, clk=>clk, reset=>reset, write_en=>write_en_4, data_out=>data_out_4);
    reg_5: reg_16_bits port map(data_in=>data_in, clk=>clk, reset=>reset, write_en=>write_en_5, data_out=>data_out_5);
    reg_6: reg_16_bits port map(data_in=>data_in, clk=>clk, reset=>reset, write_en=>write_en_6, data_out=>data_out_6);
    reg_7: reg_16_bits port map(data_in=>data_in, clk=>clk, reset=>reset, write_en=>write_en_7, data_out=>data_out_7);
    
    reg_data_a <= data_out_0 when selec_reg_a = "000" else
                  data_out_1 when selec_reg_a = "001" else
                  data_out_2 when selec_reg_a = "010" else
                  data_out_3 when selec_reg_a = "011" else
                  data_out_4 when selec_reg_a = "100" else
                  data_out_5 when selec_reg_a = "101" else
                  data_out_6 when selec_reg_a = "110" else
                  data_out_7 when selec_reg_a = "111" else
                  "0000000000000000";
                
    reg_data_b <= data_out_0 when selec_reg_b = "000" else
                  data_out_1 when selec_reg_b = "001" else
                  data_out_2 when selec_reg_b = "010" else
                  data_out_3 when selec_reg_b = "011" else
                  data_out_4 when selec_reg_b = "100" else
                  data_out_5 when selec_reg_b = "101" else
                  data_out_6 when selec_reg_b = "110" else
                  data_out_7 when selec_reg_b = "111" else
                  "0000000000000000";

    write_en_0 <= '0'; -- Always connected to GND
    write_en_1 <= write_en when selec_reg_write = "001" else '0';
    write_en_2 <= write_en when selec_reg_write = "010" else '0';
    write_en_3 <= write_en when selec_reg_write = "011" else '0';
    write_en_4 <= write_en when selec_reg_write = "100" else '0';
    write_en_5 <= write_en when selec_reg_write = "101" else '0';
    write_en_6 <= write_en when selec_reg_write = "110" else '0';
    write_en_7 <= write_en when selec_reg_write = "111" else '0';

    
end architecture rtl;

microProcessador/uProcessor.vhd
library IEEE;
use IEEE.std_logic_1164.all;
use IEEE.numeric_std.all;

entity uProcessor is
    port(
      selec_ula_action:                         in unsigned (1 downto 0);
      ula_src_b:                                in unsigned (1 downto 0);
      selec_reg_a, selec_reg_b:                 in unsigned (2 downto 0);
      selec_reg_write:                          in unsigned (2 downto 0);
      write_reg_en, clk, reset:                 in std_logic;
      output_ula, output_ula_2:                 out unsigned(15 downto 0);
      equal, greater_a, a_negative, b_negative: out std_logic
    );
end entity uProcessor;

architecture rtl of uProcessor is
    component reg_bank is
        port
        (
            selec_reg_a     : IN unsigned (2 downto 0);
            selec_reg_b     : IN unsigned (2 downto 0);
            selec_reg_write : IN unsigned (2 downto 0);
            data_in         : IN unsigned (15 downto 0);
            write_en        : IN std_logic ;
            clk             : IN std_logic ;
            reset           : IN std_logic ;
            reg_data_a      : OUT unsigned (15 downto 0);
            reg_data_b      : OUT unsigned (15 downto 0)
        );
    end component;
    
    component ula is
        port
        (
            a          : IN unsigned (15 downto 0);
            b          : IN unsigned (15 downto 0);
            selec      : IN unsigned (1 downto 0);
            output     : OUT unsigned (15 downto 0);
            output2    : out unsigned(15 downto 0);
            equal      : OUT std_logic ;
            greater_a  : OUT std_logic ;
            a_negative : OUT std_logic ;
            b_negative : OUT std_logic
        );
    end component;
    
    signal reg_data_a_sig, reg_data_b_sig, src_b_mux_output, output_ula_sig: unsigned (15 downto 0);
    
begin
    register_bank: reg_bank port map(selec_reg_a=>selec_reg_a, selec_reg_b=>selec_reg_b, selec_reg_write=>selec_reg_write, data_in=>output_ula_sig, write_en=>write_reg_en, clk=>clk, reset=>reset, reg_data_a=>reg_data_a_sig, reg_data_b=>reg_data_b_sig);
    arithmetic_lu: ula port map(a=>reg_data_a_sig, b=>src_b_mux_output, selec=>selec_ula_action, output=> output_ula_sig, output2=> output_ula_2, equal=> equal, greater_a=> greater_a, a_negative=> a_negative, b_negative=> b_negative);

    
    output_ula <= output_ula_sig;
    
    src_b_mux_output <= reg_data_b_sig     when ula_src_b = "00" else
                        "0000000000000100" when ula_src_b = "01" else
                        "0000000000000000";
    
end architecture rtl;

microProcessador/uProcessor_testbench.vhd
library IEEE;
use IEEE.std_logic_1164.all;
use IEEE.numeric_std.all;

entity uProcessor_testbench is
end entity uProcessor_testbench;

architecture rtl of uProcessor_testbench is
    component uProcessor is
        port
        (
            selec_ula_action : IN unsigned (1 downto 0);
            ula_src_b        : IN unsigned (1 downto 0);
            selec_reg_a      : IN unsigned (2 downto 0);
            selec_reg_b      : IN unsigned (2 downto 0);
            selec_reg_write  : IN unsigned (2 downto 0);
            write_reg_en     : IN std_logic ;
            clk              : IN std_logic ;
            reset            : IN std_logic ;
            output_ula       : OUT unsigned (15 downto 0);
            output_ula_2     : OUT unsigned (15 downto 0);
            equal            : OUT std_logic ;
            greater_a        : OUT std_logic ;
            a_negative       : OUT std_logic ;
            b_negative       : OUT std_logic
        );
    end component;
    
    constant time_period: time := 100 fs;
    
    signal selec_ula_action, ula_src_b: unsigned (1 downto 0);
    signal selec_reg_a, selec_reg_b, selec_reg_write: unsigned (2 downto 0);
    signal output_ula, output_ula_2: unsigned (15 downto 0);
    signal write_reg_en, clk, reset, equal, greater_a, a_negative, b_negative, finished: std_logic;
    
begin

    uut: uProcessor port map(
        selec_ula_action=> selec_ula_action,
        ula_src_b       => ula_src_b       ,
        selec_reg_a     => selec_reg_a     ,
        selec_reg_b     => selec_reg_b     ,
        selec_reg_write => selec_reg_write ,
        write_reg_en    => write_reg_en    ,
        clk             => clk             ,
        reset           => reset           ,
        output_ula      => output_ula      ,
        output_ula_2    => output_ula_2    ,
        equal           => equal           ,
        greater_a       => greater_a       ,
        a_negative      => a_negative      ,
        b_negative      => b_negative
    );
    
    reset_global: process
    begin
        reset <= '1';
        wait for time_period;
        reset <= '0';
        wait;
    end process;
    
    simulation_time: process
    begin
        wait for 1 ns;
        finished <= '1';
        wait;
    end process;
    
    clock_behavior: process
    begin
        while finished /= '1' loop
            clk <= '0';
            wait for time_period/2;
            clk <= '1';
            wait for time_period/2;
        end loop;
        wait;
    end process;


    process
    begin
        wait for 2*time_period;
        selec_ula_action <= "00";
        ula_src_b <= "01";
        selec_reg_a <= "000";
        selec_reg_b <= "100";
        selec_reg_write <= "000";
        write_reg_en <= '0';
        wait for 2*time_period;
        selec_ula_action <= "00";
        ula_src_b <= "01";
        selec_reg_a <= "001";
        selec_reg_b <= "100";
        selec_reg_write <= "001";
        write_reg_en <= '1';
        wait for 2*time_period;
        selec_ula_action <= "00";
        ula_src_b <= "01";
        selec_reg_a <= "001";
        selec_reg_b <= "001";
        selec_reg_write <= "000";
        write_reg_en <= '1';
        wait for 2*time_period;
        selec_ula_action <= "00";
        ula_src_b <= "00";
        selec_reg_a <= "000";
        selec_reg_b <= "001";
        selec_reg_write <= "010";
        write_reg_en <= '1';
        wait for 2*time_period;
        selec_ula_action <= "00";
        ula_src_b <= "00";
        selec_reg_a <= "010";
        selec_reg_b <= "101";
        selec_reg_write <= "111";
        write_reg_en <= '1';
        wait for 2*time_period;
        selec_ula_action <= "00";
        ula_src_b <= "01";
        selec_reg_a <= "011";
        selec_reg_b <= "100";
        selec_reg_write <= "101";
        write_reg_en <= '1';
        wait for 2*time_period;
        selec_ula_action <= "00";
        ula_src_b <= "01";
        selec_reg_a <= "000";
        selec_reg_b <= "101";
        selec_reg_write <= "100";
        write_reg_en <= '1';
        wait for 2*time_period;
        selec_ula_action <= "00";
        ula_src_b <= "00";
        selec_reg_a <= "010";
        selec_reg_b <= "100";
        selec_reg_write <= "110";
        write_reg_en <= '1';
        wait for 2*time_period;
        selec_ula_action <= "00";
        ula_src_b <= "01";
        selec_reg_a <= "110";
        selec_reg_b <= "100";
        selec_reg_write <= "011";
        write_reg_en <= '1';
        wait for 2*time_period;
        selec_ula_action <= "00";
        ula_src_b <= "00";
        selec_reg_a <= "010";
        selec_reg_b <= "100";
        selec_reg_write <= "010";
        write_reg_en <= '1';
        wait for 2*time_period;
        write_reg_en <= '0';
        wait;
    end process;
end architecture rtl;

microProcessador/uProcessor_testbench.vcd
$date
  Thu Sep 29 21:17:12 2022
$end
$version
  GHDL v0
$end
$timescale
  1 fs
$end
$scope module standard $end
$upscope $end
$scope module textio $end
$upscope $end
$scope module std_logic_1164 $end
$upscope $end
$scope module numeric_std $end
$upscope $end
$scope module uprocessor_testbench $end
$var reg 2 ! selec_ula_action[1:0] $end
$var reg 2 " ula_src_b[1:0] $end
$var reg 3 # selec_reg_a[2:0] $end
$var reg 3 $ selec_reg_b[2:0] $end
$var reg 3 % selec_reg_write[2:0] $end
$var reg 16 & output_ula[15:0] $end
$var reg 16 ' output_ula_2[15:0] $end
$var reg 1 ( write_reg_en $end
$var reg 1 ) clk $end
$var reg 1 * reset $end
$var reg 1 + equal $end
$var reg 1 , greater_a $end
$var reg 1 - a_negative $end
$var reg 1 . b_negative $end
$var reg 1 / finished $end
$scope module uut $end
$var reg 2 0 selec_ula_action[1:0] $end
$var reg 2 1 ula_src_b[1:0] $end
$var reg 3 2 selec_reg_a[2:0] $end
$var reg 3 3 selec_reg_b[2:0] $end
$var reg 3 4 selec_reg_write[2:0] $end
$var reg 1 5 write_reg_en $end
$var reg 1 6 clk $end
$var reg 1 7 reset $end
$var reg 16 8 output_ula[15:0] $end
$var reg 16 9 output_ula_2[15:0] $end
$var reg 1 : equal $end
$var reg 1 ; greater_a $end
$var reg 1 < a_negative $end
$var reg 1 = b_negative $end
$var reg 16 > reg_data_a_sig[15:0] $end
$var reg 16 ? reg_data_b_sig[15:0] $end
$var reg 16 @ src_b_mux_output[15:0] $end
$var reg 16 A output_ula_sig[15:0] $end
$scope module register_bank $end
$var reg 3 B selec_reg_a[2:0] $end
$var reg 3 C selec_reg_b[2:0] $end
$var reg 3 D selec_reg_write[2:0] $end
$var reg 16 E data_in[15:0] $end
$var reg 1 F write_en $end
$var reg 1 G clk $end
$var reg 1 H reset $end
$var reg 16 I reg_data_a[15:0] $end
$var reg 16 J reg_data_b[15:0] $end
$var reg 16 K data_out_0[15:0] $end
$var reg 16 L data_out_1[15:0] $end
$var reg 16 M data_out_2[15:0] $end
$var reg 16 N data_out_3[15:0] $end
$var reg 16 O data_out_4[15:0] $end
$var reg 16 P data_out_5[15:0] $end
$var reg 16 Q data_out_6[15:0] $end
$var reg 16 R data_out_7[15:0] $end
$var reg 1 S write_en_0 $end
$var reg 1 T write_en_1 $end
$var reg 1 U write_en_2 $end
$var reg 1 V write_en_3 $end
$var reg 1 W write_en_4 $end
$var reg 1 X write_en_5 $end
$var reg 1 Y write_en_6 $end
$var reg 1 Z write_en_7 $end
$scope module reg_0 $end
$var reg 16 [ data_in[15:0] $end
$var reg 1 \ clk $end
$var reg 1 ] reset $end
$var reg 1 ^ write_en $end
$var reg 16 _ data_out[15:0] $end
$var reg 16 ` registring[15:0] $end
$upscope $end
$scope module reg_1 $end
$var reg 16 a data_in[15:0] $end
$var reg 1 b clk $end
$var reg 1 c reset $end
$var reg 1 d write_en $end
$var reg 16 e data_out[15:0] $end
$var reg 16 f registring[15:0] $end
$upscope $end
$scope module reg_2 $end
$var reg 16 g data_in[15:0] $end
$var reg 1 h clk $end
$var reg 1 i reset $end
$var reg 1 j write_en $end
$var reg 16 k data_out[15:0] $end
$var reg 16 l registring[15:0] $end
$upscope $end
$scope module reg_3 $end
$var reg 16 m data_in[15:0] $end
$var reg 1 n clk $end
$var reg 1 o reset $end
$var reg 1 p write_en $end
$var reg 16 q data_out[15:0] $end
$var reg 16 r registring[15:0] $end
$upscope $end
$scope module reg_4 $end
$var reg 16 s data_in[15:0] $end
$var reg 1 t clk $end
$var reg 1 u reset $end
$var reg 1 v write_en $end
$var reg 16 w data_out[15:0] $end
$var reg 16 x registring[15:0] $end
$upscope $end
$scope module reg_5 $end
$var reg 16 y data_in[15:0] $end
$var reg 1 z clk $end
$var reg 1 { reset $end
$var reg 1 | write_en $end
$var reg 16 } data_out[15:0] $end
$var reg 16 !" registring[15:0] $end
$upscope $end
$scope module reg_6 $end
$var reg 16 "" data_in[15:0] $end
$var reg 1 #" clk $end
$var reg 1 $" reset $end
$var reg 1 %" write_en $end
$var reg 16 &" data_out[15:0] $end
$var reg 16 '" registring[15:0] $end
$upscope $end
$scope module reg_7 $end
$var reg 16 (" data_in[15:0] $end
$var reg 1 )" clk $end
$var reg 1 *" reset $end
$var reg 1 +" write_en $end
$var reg 16 ," data_out[15:0] $end
$var reg 16 -" registring[15:0] $end
$upscope $end
$upscope $end
$scope module arithmetic_lu $end
$var reg 16 ." a[15:0] $end
$var reg 16 /" b[15:0] $end
$var reg 2 0" selec[1:0] $end
$var reg 16 1" output[15:0] $end
$var reg 16 2" output2[15:0] $end
$var reg 1 3" equal $end
$var reg 1 4" greater_a $end
$var reg 1 5" a_negative $end
$var reg 1 6" b_negative $end
$upscope $end
$upscope $end
$upscope $end
$enddefinitions $end
#0
bUU !
bUU "
bUUU #
bUUU $
bUUU %
b0000000000000000 &
b0000000000000000 '
U(
0)
1*
1+
0,
0-
0.
U/
bUU 0
bUU 1
bUUU 2
bUUU 3
bUUU 4
U5
06
17
b0000000000000000 8
b0000000000000000 9
1:
0;
0<
0=
b0000000000000000 >
b0000000000000000 ?
b0000000000000000 @
b0000000000000000 A
bUUU B
bUUU C
bUUU D
b0000000000000000 E
UF
0G
1H
b0000000000000000 I
b0000000000000000 J
b0000000000000000 K
b0000000000000000 L
b0000000000000000 M
b0000000000000000 N
b0000000000000000 O
b0000000000000000 P
b0000000000000000 Q
b0000000000000000 R
0S
0T
0U
0V
0W
0X
0Y
0Z
b0000000000000000 [
0\
1]
0^
b0000000000000000 _
b0000000000000000 `
b0000000000000000 a
0b
1c
0d
b0000000000000000 e
b0000000000000000 f
b0000000000000000 g
0h
1i
0j
b0000000000000000 k
b0000000000000000 l
b0000000000000000 m
0n
1o
0p
b0000000000000000 q
b0000000000000000 r
b0000000000000000 s
0t
1u
0v
b0000000000000000 w
b0000000000000000 x
b0000000000000000 y
0z
1{
0|
b0000000000000000 }
b0000000000000000 !"
b0000000000000000 ""
0#"
1$"
0%"
b0000000000000000 &"
b0000000000000000 '"
b0000000000000000 ("
0)"
1*"
0+"
b0000000000000000 ,"
b0000000000000000 -"
b0000000000000000 ."
b0000000000000000 /"
bUU 0"
b0000000000000000 1"
b0000000000000000 2"
13"
04"
05"
06"
#50
1)
16
1G
1\
1b
1h
1n
1t
1z
1#"
1)"
#100
0)
0*
06
07
0G
0H
0\
0]
0b
0c
0h
0i
0n
0o
0t
0u
0z
0{
0#"
0$"
0)"
0*"
#150
1)
16
1G
1\
1b
1h
1n
1t
1z
1#"
1)"
#200
b00 !
b01 "
b000 #
b100 $
b000 %
b0000000000000100 &
b0000000000000100 '
0(
0)
0+
b00 0
b01 1
b000 2
b100 3
b000 4
05
06
b0000000000000100 8
b0000000000000100 9
0:
b0000000000000100 @
b0000000000000100 A
b000 B
b100 C
b000 D
b0000000000000100 E
0F
0G
b0000000000000100 [
0\
b0000000000000100 a
0b
b0000000000000100 g
0h
b0000000000000100 m
0n
b0000000000000100 s
0t
b0000000000000100 y
0z
b0000000000000100 ""
0#"
b0000000000000100 ("
0)"
b0000000000000100 /"
b00 0"
b0000000000000100 1"
b0000000000000100 2"
03"
#250
1)
16
1G
1\
1b
1h
1n
1t
1z
1#"
1)"
#300
0)
06
0G
0\
0b
0h
0n
0t
0z
0#"
0)"
#350
1)
16
1G
1\
1b
1h
1n
1t
1z
1#"
1)"
#400
b001 #
b001 %
1(
0)
b001 2
b001 4
15
06
b001 B
b001 D
1F
0G
1T
0\
0b
1d
0h
0n
0t
0z
0#"
0)"
#450
b0000000000001000 &
b0000000000001000 '
1)
1+
16
b0000000000001000 8
b0000000000001000 9
1:
b0000000000000100 >
b0000000000001000 A
b0000000000001000 E
1G
b0000000000000100 I
b0000000000000100 L
b0000000000001000 [
1\
b0000000000001000 a
1b
b0000000000000100 e
b0000000000000100 f
b0000000000001000 g
1h
b0000000000001000 m
1n
b0000000000001000 s
1t
b0000000000001000 y
1z
b0000000000001000 ""
1#"
b0000000000001000 ("
1)"
b0000000000000100 ."
b0000000000001000 1"
b0000000000001000 2"
13"
#500
0)
06
0G
0\
0b
0h
0n
0t
0z
0#"
0)"
#550
b0000000000001100 &
b0000000000001100 '
1)
0+
1,
16
b0000000000001100 8
b0000000000001100 9
0:
1;
b0000000000001000 >
b0000000000001100 A
b0000000000001100 E
1G
b0000000000001000 I
b0000000000001000 L
b0000000000001100 [
1\
b0000000000001100 a
1b
b0000000000001000 e
b0000000000001000 f
b0000000000001100 g
1h
b0000000000001100 m
1n
b0000000000001100 s
1t
b0000000000001100 y
1z
b0000000000001100 ""
1#"
b0000000000001100 ("
1)"
b0000000000001000 ."
b0000000000001100 1"
b0000000000001100 2"
03"
14"
#600
b001 $
b000 %
0)
b001 3
b000 4
06
b0000000000001000 ?
b001 C
b000 D
0G
b0000000000001000 J
0T
0\
0b
0d
0h
0n
0t
0z
0#"
0)"
#650
1)
16
1G
1\
1b
1h
1n
1t
1z
1#"
1)"
#700
0)
06
0G
0\
0b
0h
0n
0t
0z
0#"
0)"
#750
1)
16
1G
1\
1b
1h
1n
1t
1z
1#"
1)"
#800
b00 "
b000 #
b010 %
b0000000000001000 &
b0000000000001000 '
0)
0,
b00 1
b000 2
b010 4
06
b0000000000001000 8
b0000000000001000 9
0;
b0000000000000000 >
b0000000000001000 @
b0000000000001000 A
b000 B
b010 D
b0000000000001000 E
0G
b0000000000000000 I
1U
b0000000000001000 [
0\
b0000000000001000 a
0b
b0000000000001000 g
0h
1j
b0000000000001000 m
0n
b0000000000001000 s
0t
b0000000000001000 y
0z
b0000000000001000 ""
0#"
b0000000000001000 ("
0)"
b0000000000000000 ."
b0000000000001000 /"
b0000000000001000 1"
b0000000000001000 2"
04"
#850
1)
16
1G
b0000000000001000 M
1\
1b
1h
b0000000000001000 k
b0000000000001000 l
1n
1t
1z
1#"
1)"
#900
0)
06
0G
0\
0b
0h
0n
0t
0z
0#"
0)"
#950
1)
16
1G
1\
1b
1h
1n
1t
1z
1#"
1)"
#1000
b010 #
b101 $
b111 %
b0000000000001000 &
b0000000000001000 '
0)
0+
1,
b010 2
b101 3
b111 4
06
b0000000000001000 8
b0000000000001000 9
0:
1;
b0000000000001000 >
b0000000000000000 ?
b0000000000000000 @
b0000000000001000 A
b010 B
b101 C
b111 D
b0000000000001000 E
0G
b0000000000001000 I
b0000000000000000 J
0U
1Z
b0000000000001000 [
0\
b0000000000001000 a
0b
b0000000000001000 g
0h
0j
b0000000000001000 m
0n
b0000000000001000 s
0t
b0000000000001000 y
0z
b0000000000001000 ""
0#"
b0000000000001000 ("
0)"
1+"
b0000000000001000 ."
b0000000000000000 /"
b0000000000001000 1"
b0000000000001000 2"
03"
14"
#1050
1)
16
1G
b0000000000001000 R
1\
1b
1h
1n
1t
1z
1#"
1)"
b0000000000001000 ,"
b0000000000001000 -"
#1100
0)
06
0G
0\
0b
0h
0n
0t
0z
0#"
0)"
#1150
1)
16
1G
1\
1b
1h
1n
1t
1z
1#"
1)"
#1200
b01 "
b011 #
b100 $
b101 %
b0000000000000100 &
b0000000000000100 '
0)
0,
b01 1
b011 2
b100 3
b101 4
06
b0000000000000100 8
b0000000000000100 9
0;
b0000000000000000 >
b0000000000000100 @
b0000000000000100 A
b011 B
b100 C
b101 D
b0000000000000100 E
0G
b0000000000000000 I
1X
0Z
b0000000000000100 [
0\
b0000000000000100 a
0b
b0000000000000100 g
0h
b0000000000000100 m
0n
b0000000000000100 s
0t
b0000000000000100 y
0z
1|
b0000000000000100 ""
0#"
b0000000000000100 ("
0)"
0+"
b0000000000000000 ."
b0000000000000100 /"
b0000000000000100 1"
b0000000000000100 2"
04"
#1250
1)
16
1G
b0000000000000100 P
1\
1b
1h
1n
1t
1z
b0000000000000100 }
b0000000000000100 !"
1#"
1)"
#1300
0)
06
0G
0\
0b
0h
0n
0t
0z
0#"
0)"
#1350
1)
16
1G
1\
1b
1h
1n
1t
1z
1#"
1)"
#1400
b000 #
b101 $
b100 %
0)
b000 2
b101 3
b100 4
06
b0000000000000100 ?
b000 B
b101 C
b100 D
0G
b0000000000000100 J
1W
0X
0\
0b
0h
0n
0t
1v
0z
0|
0#"
0)"
#1450
1)
16
1G
b0000000000000100 O
1\
1b
1h
1n
1t
b0000000000000100 w
b0000000000000100 x
1z
1#"
1)"
#1500
0)
06
0G
0\
0b
0h
0n
0t
0z
0#"
0)"
#1550
1)
16
1G
1\
1b
1h
1n
1t
1z
1#"
1)"
#1600
b00 "
b010 #
b100 $
b110 %
b0000000000001100 &
b0000000000001100 '
0)
1,
b00 1
b010 2
b100 3
b110 4
06
b0000000000001100 8
b0000000000001100 9
1;
b0000000000001000 >
b0000000000001100 A
b010 B
b100 C
b110 D
b0000000000001100 E
0G
b0000000000001000 I
0W
1Y
b0000000000001100 [
0\
b0000000000001100 a
0b
b0000000000001100 g
0h
b0000000000001100 m
0n
b0000000000001100 s
0t
0v
b0000000000001100 y
0z
b0000000000001100 ""
0#"
1%"
b0000000000001100 ("
0)"
b0000000000001000 ."
b0000000000001100 1"
b0000000000001100 2"
14"
#1650
1)
16
1G
b0000000000001100 Q
1\
1b
1h
1n
1t
1z
1#"
b0000000000001100 &"
b0000000000001100 '"
1)"
#1700
0)
06
0G
0\
0b
0h
0n
0t
0z
0#"
0)"
#1750
1)
16
1G
1\
1b
1h
1n
1t
1z
1#"
1)"
#1800
b01 "
b110 #
b011 %
b0000000000010000 &
b0000000000010000 '
0)
b01 1
b110 2
b011 4
06
b0000000000010000 8
b0000000000010000 9
b0000000000001100 >
b0000000000010000 A
b110 B
b011 D
b0000000000010000 E
0G
b0000000000001100 I
1V
0Y
b0000000000010000 [
0\
b0000000000010000 a
0b
b0000000000010000 g
0h
b0000000000010000 m
0n
1p
b0000000000010000 s
0t
b0000000000010000 y
0z
b0000000000010000 ""
0#"
0%"
b0000000000010000 ("
0)"
b0000000000001100 ."
b0000000000010000 1"
b0000000000010000 2"
#1850
1)
16
1G
b0000000000010000 N
1\
1b
1h
1n
b0000000000010000 q
b0000000000010000 r
1t
1z
1#"
1)"
#1900
0)
06
0G
0\
0b
0h
0n
0t
0z
0#"
0)"
#1950
1)
16
1G
1\
1b
1h
1n
1t
1z
1#"
1)"
#2000
b00 "
b010 #
b010 %
b0000000000001100 &
b0000000000001100 '
0)
b00 1
b010 2
b010 4
06
b0000000000001100 8
b0000000000001100 9
b0000000000001000 >
b0000000000001100 A
b010 B
b010 D
b0000000000001100 E
0G
b0000000000001000 I
1U
0V
b0000000000001100 [
0\
b0000000000001100 a
0b
b0000000000001100 g
0h
1j
b0000000000001100 m
0n
0p
b0000000000001100 s
0t
b0000000000001100 y
0z
b0000000000001100 ""
0#"
b0000000000001100 ("
0)"
b0000000000001000 ."
b0000000000001100 1"
b0000000000001100 2"
#2050
b0000000000010000 &
b0000000000010000 '
1)
16
b0000000000010000 8
b0000000000010000 9
b0000000000001100 >
b0000000000010000 A
b0000000000010000 E
1G
b0000000000001100 I
b0000000000001100 M
b0000000000010000 [
1\
b0000000000010000 a
1b
b0000000000010000 g
1h
b0000000000001100 k
b0000000000001100 l
b0000000000010000 m
1n
b0000000000010000 s
1t
b0000000000010000 y
1z
b0000000000010000 ""
1#"
b0000000000010000 ("
1)"
b0000000000001100 ."
b0000000000010000 1"
b0000000000010000 2"
#2100
0)
06
0G
0\
0b
0h
0n
0t
0z
0#"
0)"
#2150
b0000000000010100 &
b0000000000010100 '
1)
16
b0000000000010100 8
b0000000000010100 9
b0000000000010000 >
b0000000000010100 A
b0000000000010100 E
1G
b0000000000010000 I
b0000000000010000 M
b0000000000010100 [
1\
b0000000000010100 a
1b
b0000000000010100 g
1h
b0000000000010000 k
b0000000000010000 l
b0000000000010100 m
1n
b0000000000010100 s
1t
b0000000000010100 y
1z
b0000000000010100 ""
1#"
b0000000000010100 ("
1)"
b0000000000010000 ."
b0000000000010100 1"
b0000000000010100 2"
#2200
0(
0)
05
06
0F
0G
0U
0\
0b
0h
0j
0n
0t
0z
0#"
0)"
